ua_email_client/__init__.py
ua_email_client/tests/templates/invalid.template.html
ua_email_client/tests/templates/invalid_type.md
ua_email_client/tests/templates/test_template.html
ua_email_client/tests/test_ua_email_client.py
ua_email_client/ua_email_client.py
ua_email_client-0.1.9.dist-info/LICENSE
ua_email_client-0.1.9.dist-info/METADATA
ua_email_client-0.1.9.dist-info/WHEEL
ua_email_client-0.1.9.dist-info/RECORD
