Metadata-Version: 2.1
Name: ua-email-client
Version: 0.1.9
Summary: Provides easy interface for sending emails through Amazons Simple Email Service.
Author: Your Name
Author-email: you@example.com
Requires-Python: >=3.11,<4.0
Classifier: Programming Language :: Python :: 3
Classifier: Programming Language :: Python :: 3.11
Classifier: Programming Language :: Python :: 3.12
Requires-Dist: boto3 (>=1.29.7,<2.0.0)
Requires-Dist: datetime (>=5.3,<6.0)
Requires-Dist: jinja2 (>=3.1.2,<4.0.0)
Requires-Dist: nose (>=1.3.7,<2.0.0)
